Taest/test1.py
Taest/test2.py
Taest-0.0.0.2.dist-info/METADATA
Taest-0.0.0.2.dist-info/WHEEL
Taest-0.0.0.2.dist-info/top_level.txt
Taest-0.0.0.2.dist-info/RECORD
