Metadata-Version: 2.1
Name: Taest
Version: 0.0.0.2
Summary: My First Test Package
Home-page: https://lingua.blog.me/…
Author: TaeKyun Kim
Author-email: ktk4000@gmail.com
License: MIT
Requires-Python: >=3.7
